[
  {
    "name": "All The Smoke",
    "icon": "https://yt3.ggpht.com/QGmLgC4Be3XV8rtmWwbQGL1pY3idpfakkDpetsbSn5moO5fjLzuX7Jfn2UArpQ0-5oZZXmckHJU=s800-c-k-c0x00ffffff-no-rj",
    "views_28": 34263513,
    "views_prev_28": 40401496,
    "subs_28": 30833,
    "subs_prev_28": 35093,
    "uploads_28": 78,
    "uploads_prev_28": 97,
    "revenue_28": 49070.173,
    "cpm_28": 8.726346153846155,
    "revenue_prev_28": 55500.619000000006,
    "cpm_prev_28": 8.027607142857144,
    "revenue_365": 259267.22500000006,
    "cpm_365": 8.753765840220389,
    "revenue_2022": 0,
    "cpm_2022": 0.0,
    "revenue_2023": 0,
    "cpm_2023": 0.0,
    "revenue_2024": 230807.17100000003,
    "cpm_2024": 8.262669398907105
  },
  {
    "name": "KG Certified",
    "icon": "https://yt3.ggpht.com/yvxSfblgWpSADo_EzMMFh7vYylz_Gjp-sXqP56cvVLO8Zz6HYGL1kv3xt6ynBPwlEzbae9vv=s800-c-k-c0x00ffffff-no-rj",
    "views_28": 4791720,
    "views_prev_28": 2369747,
    "subs_28": 10945,
    "subs_prev_28": 8760,
    "uploads_28": 46,
    "uploads_prev_28": 50,
    "revenue_28": 5866.551,
    "cpm_28": 7.3202307692307675,
    "revenue_prev_28": 6736.114999999998,
    "cpm_prev_28": 7.171857142857142,
    "revenue_365": 49005.599000000024,
    "cpm_365": 7.462831955922865,
    "revenue_2022": 0,
    "cpm_2022": 0.0,
    "revenue_2023": 15283.382000000001,
    "cpm_2023": 6.318002739726029,
    "revenue_2024": 19073.627999999997,
    "cpm_2024": 7.3737732240437195
  },
  {
    "name": "Morning Kombat",
    "icon": "https://yt3.ggpht.com/qGb1QlPmdErjmL0Nd6cbMsC12FPpTijtrHuY43y9DWKdhsTUll8XkmJNyX30LkWGuRjFUp7V=s800-c-k-c0x00ffffff-no-rj",
    "views_28": 474953,
    "views_prev_28": 449859,
    "subs_28": 209,
    "subs_prev_28": 96,
    "uploads_28": 8,
    "uploads_prev_28": 8,
    "revenue_28": 2621.2709999999993,
    "cpm_28": 6.321461538461539,
    "revenue_prev_28": 3086.866,
    "cpm_prev_28": 6.449714285714285,
    "revenue_365": 16502.52800000001,
    "cpm_365": 2.774754820936638,
    "revenue_2022": 0,
    "cpm_2022": 0.0,
    "revenue_2023": 0,
    "cpm_2023": 0.0,
    "revenue_2024": 1386.8600000000001,
    "cpm_2024": 0.22930054644808745
  },
  {
    "name": "All The Smoke Fight",
    "icon": "https://yt3.ggpht.com/tyRwrGfrQkd57eiXOUMjiHmlh6zTLJmgZ9yb5oCbUDbWdjxS3qloyti2fW8WIe-TmfgRbDo3hw=s800-c-k-c0x00ffffff-no-rj",
    "views_28": 2931447,
    "views_prev_28": 1912049,
    "subs_28": 3395,
    "subs_prev_28": 1625,
    "uploads_28": 39,
    "uploads_prev_28": 27,
    "revenue_28": 10765.108000000002,
    "cpm_28": 6.529923076923078,
    "revenue_prev_28": 9151.481,
    "cpm_prev_28": 6.118750000000001,
    "revenue_365": 124175.00499999992,
    "cpm_365": 6.499942148760325,
    "revenue_2022": 0,
    "cpm_2022": 0.0,
    "revenue_2023": 0,
    "cpm_2023": 0.0,
    "revenue_2024": 74177.54999999996,
    "cpm_2024": 3.8079398907103834
  },
  {
    "name": "Ring Champs",
    "icon": "https://yt3.ggpht.com/BbGdlZ2wNgCpzri02772HfpWsK-eGUOQ-16lm4dN_H6ACEmKW8akOm_F2IcSX2TNcW-QpznNqg=s800-c-k-c0x00ffffff-no-rj",
    "views_28": 159932,
    "views_prev_28": 86537,
    "subs_28": 1368,
    "subs_prev_28": 549,
    "uploads_28": 26,
    "uploads_prev_28": 23,
    "revenue_28": 988.06,
    "cpm_28": 2.836307692307692,
    "revenue_prev_28": 0,
    "cpm_prev_28": 0.0,
    "revenue_365": 988.06,
    "cpm_365": 0.20315151515151514,
    "revenue_2022": 0,
    "cpm_2022": 0.0,
    "revenue_2023": 0,
    "cpm_2023": 0.0,
    "revenue_2024": 0,
    "cpm_2024": 0.0
  },
  {
    "name": "Victor Oladipo",
    "icon": "https://yt3.ggpht.com/f-EEPiNJ33jMljawz5ikYenlzou4f-NLp2-UH-yL89WtYCwqGpU3nb32Ftx465ifap1vYMrg=s800-c-k-c0x00ffffff-no-rj",
    "views_28": 328172,
    "views_prev_28": 37978,
    "subs_28": 1180,
    "subs_prev_28": -37,
    "uploads_28": 64,
    "uploads_prev_28": 21,
    "revenue_28": 617.063,
    "cpm_28": 6.636153846153844,
    "revenue_prev_28": 12.665000000000001,
    "cpm_prev_28": 2.3825714285714286,
    "revenue_365": 629.7280000000001,
    "cpm_365": 0.6590964187327824,
    "revenue_2022": 48.87700000000006,
    "cpm_2022": 4.890561643835619,
    "revenue_2023": 18.414000000000012,
    "cpm_2023": 3.963180821917809,
    "revenue_2024": 0,
    "cpm_2024": 0.0
  },
  {
    "name": "San Antonio Spurs",
    "icon": "https://yt3.ggpht.com/dc6Tx4eGfjTkg8tpgEfNbfHwGU0FZFIKrBAmJ__0OFp15mr55gEIszxlM9IYcrfWg1zTDR69WRE=s800-c-k-c0x00ffffff-no-rj",
    "views_28": 0,
    "views_prev_28": 0,
    "subs_28": 0,
    "subs_prev_28": 0,
    "uploads_28": 0,
    "uploads_prev_28": 0,
    "revenue_28": 0,
    "cpm_28": 0,
    "revenue_prev_28": 0,
    "cpm_prev_28": 0,
    "revenue_365": 0,
    "cpm_365": 0,
    "revenue_2022": 0,
    "cpm_2022": 0,
    "revenue_2023": 0,
    "cpm_2023": 0,
    "revenue_2024": 0,
    "cpm_2024": 0
  }
]