[
  {
    "name": "All The Smoke",
    "icon": "https://yt3.ggpht.com/QGmLgC4Be3XV8rtmWwbQGL1pY3idpfakkDpetsbSn5moO5fjLzuX7Jfn2UArpQ0-5oZZXmckHJU=s800-c-k-c0x00ffffff-no-rj",
    "views_28": 14389648,
    "views_prev_28": 42009323,
    "subs_28": 12054,
    "subs_prev_28": 37066,
    "uploads_28": 85,
    "uploads_prev_28": 79,
    "revenue_28": 26205.679,
    "cpm_28": 9.945115384615384,
    "revenue_prev_28": 58100.10200000001,
    "cpm_prev_28": 8.694357142857145,
    "revenue_365": 270844.98100000015,
    "cpm_365": 8.949809917355378,
    "revenue_2022": 0,
    "cpm_2022": 0.0,
    "revenue_2023": 0,
    "cpm_2023": 0.0,
    "revenue_2024": 230807.17100000003,
    "cpm_2024": 8.262669398907105
  },
  {
    "name": "KG Certified",
    "icon": "https://yt3.ggpht.com/yvxSfblgWpSADo_EzMMFh7vYylz_Gjp-sXqP56cvVLO8Zz6HYGL1kv3xt6ynBPwlEzbae9vv=s800-c-k-c0x00ffffff-no-rj",
    "views_28": 4291202,
    "views_prev_28": 5139149,
    "subs_28": 5540,
    "subs_prev_28": 12754,
    "uploads_28": 48,
    "uploads_prev_28": 46,
    "revenue_28": 4971.207000000001,
    "cpm_28": 7.588730769230769,
    "revenue_prev_28": 7017.791999999999,
    "cpm_prev_28": 7.26275,
    "revenue_365": 52500.66000000001,
    "cpm_365": 7.484961432506887,
    "revenue_2022": 0,
    "cpm_2022": 0.0,
    "revenue_2023": 15283.382000000001,
    "cpm_2023": 6.318002739726029,
    "revenue_2024": 19073.627999999997,
    "cpm_2024": 7.3737732240437195
  },
  {
    "name": "Morning Kombat",
    "icon": "https://yt3.ggpht.com/qGb1QlPmdErjmL0Nd6cbMsC12FPpTijtrHuY43y9DWKdhsTUll8XkmJNyX30LkWGuRjFUp7V=s800-c-k-c0x00ffffff-no-rj",
    "views_28": 463246,
    "views_prev_28": 526615,
    "subs_28": 190,
    "subs_prev_28": 257,
    "uploads_28": 19,
    "uploads_prev_28": 8,
    "revenue_28": 2967.895000000001,
    "cpm_28": 6.9238461538461555,
    "revenue_prev_28": 2938.2260000000006,
    "cpm_prev_28": 6.325464285714288,
    "revenue_365": 19414.489000000016,
    "cpm_365": 3.251969696969696,
    "revenue_2022": 0,
    "cpm_2022": 0.0,
    "revenue_2023": 0,
    "cpm_2023": 0.0,
    "revenue_2024": 1386.8600000000001,
    "cpm_2024": 0.22930054644808745
  },
  {
    "name": "All The Smoke Fight",
    "icon": "https://yt3.ggpht.com/tyRwrGfrQkd57eiXOUMjiHmlh6zTLJmgZ9yb5oCbUDbWdjxS3qloyti2fW8WIe-TmfgRbDo3hw=s800-c-k-c0x00ffffff-no-rj",
    "views_28": 1888263,
    "views_prev_28": 2975420,
    "subs_28": 1203,
    "subs_prev_28": 3366,
    "uploads_28": 32,
    "uploads_prev_28": 35,
    "revenue_28": 7660.243,
    "cpm_28": 6.460076923076924,
    "revenue_prev_28": 10782.519,
    "cpm_prev_28": 6.383071428571427,
    "revenue_365": 128131.90799999994,
    "cpm_365": 6.723404958677686,
    "revenue_2022": 0,
    "cpm_2022": 0.0,
    "revenue_2023": 0,
    "cpm_2023": 0.0,
    "revenue_2024": 74177.54999999996,
    "cpm_2024": 3.8079398907103834
  },
  {
    "name": "Ring Champs",
    "icon": "https://yt3.ggpht.com/BbGdlZ2wNgCpzri02772HfpWsK-eGUOQ-16lm4dN_H6ACEmKW8akOm_F2IcSX2TNcW-QpznNqg=s800-c-k-c0x00ffffff-no-rj",
    "views_28": 1776301,
    "views_prev_28": 140594,
    "subs_28": 4218,
    "subs_prev_28": 1172,
    "uploads_28": 39,
    "uploads_prev_28": 21,
    "revenue_28": 3025.174,
    "cpm_28": 6.677999999999998,
    "revenue_prev_28": 555.322,
    "cpm_prev_28": 2.3814285714285717,
    "revenue_365": 3580.496,
    "cpm_365": 0.6620055096418732,
    "revenue_2022": 0,
    "cpm_2022": 0.0,
    "revenue_2023": 0,
    "cpm_2023": 0.0,
    "revenue_2024": 0,
    "cpm_2024": 0.0
  },
  {
    "name": "Victor Oladipo",
    "icon": "https://yt3.ggpht.com/f-EEPiNJ33jMljawz5ikYenlzou4f-NLp2-UH-yL89WtYCwqGpU3nb32Ftx465ifap1vYMrg=s800-c-k-c0x00ffffff-no-rj",
    "views_28": 82951,
    "views_prev_28": 334613,
    "subs_28": 533,
    "subs_prev_28": 1135,
    "uploads_28": 0,
    "uploads_prev_28": 69,
    "revenue_28": 477.6839999999999,
    "cpm_28": 7.507999999999999,
    "revenue_prev_28": 588.9179999999999,
    "cpm_prev_28": 6.569642857142858,
    "revenue_365": 1075.8099999999997,
    "cpm_365": 1.1753939393939392,
    "revenue_2022": 48.87700000000006,
    "cpm_2022": 4.890561643835619,
    "revenue_2023": 18.414000000000012,
    "cpm_2023": 3.963180821917809,
    "revenue_2024": 0,
    "cpm_2024": 0.0
  },
  {
    "name": "San Antonio Spurs",
    "icon": "https://yt3.ggpht.com/dc6Tx4eGfjTkg8tpgEfNbfHwGU0FZFIKrBAmJ__0OFp15mr55gEIszxlM9IYcrfWg1zTDR69WRE=s800-c-k-c0x00ffffff-no-rj",
    "views_28": 0,
    "views_prev_28": 0,
    "subs_28": 0,
    "subs_prev_28": 0,
    "uploads_28": 0,
    "uploads_prev_28": 0,
    "revenue_28": 0,
    "cpm_28": 0,
    "revenue_prev_28": 0,
    "cpm_prev_28": 0,
    "revenue_365": 0,
    "cpm_365": 0,
    "revenue_2022": 0,
    "cpm_2022": 0,
    "revenue_2023": 0,
    "cpm_2023": 0,
    "revenue_2024": 0,
    "cpm_2024": 0
  }
]