[
  {
    "name": "All The Smoke",
    "icon": "https://yt3.ggpht.com/QGmLgC4Be3XV8rtmWwbQGL1pY3idpfakkDpetsbSn5moO5fjLzuX7Jfn2UArpQ0-5oZZXmckHJU=s800-c-k-c0x00ffffff-no-rj",
    "views_28": 13919264,
    "views_prev_28": 12393201,
    "subs_28": 11667,
    "subs_prev_28": 11115,
    "uploads_28": 65,
    "uploads_prev_28": 61,
    "revenue_28": 16992.905,
    "cpm_28": 7.646461538461538,
    "revenue_prev_28": 22055.582,
    "cpm_prev_28": 8.044035714285714,
    "revenue_365": 293236.42599999986,
    "cpm_365": 8.835586776859506,
    "revenue_2022": 0,
    "cpm_2022": 0.0,
    "revenue_2023": 0,
    "cpm_2023": 0.0,
    "revenue_2024": 230807.17100000003,
    "cpm_2024": 8.262669398907105
  },
  {
    "name": "KG Certified",
    "icon": "https://yt3.ggpht.com/yvxSfblgWpSADo_EzMMFh7vYylz_Gjp-sXqP56cvVLO8Zz6HYGL1kv3xt6ynBPwlEzbae9vv=s800-c-k-c0x00ffffff-no-rj",
    "views_28": 1496233,
    "views_prev_28": 2384240,
    "subs_28": 1591,
    "subs_prev_28": 3165,
    "uploads_28": 9,
    "uploads_prev_28": 12,
    "revenue_28": 382.50100000000003,
    "cpm_28": 7.009,
    "revenue_prev_28": 865.4590000000001,
    "cpm_prev_28": 7.061464285714288,
    "revenue_365": 56318.961000000025,
    "cpm_365": 7.57287878787879,
    "revenue_2022": 0,
    "cpm_2022": 0.0,
    "revenue_2023": 15283.382000000001,
    "cpm_2023": 6.318002739726029,
    "revenue_2024": 19073.627999999997,
    "cpm_2024": 7.3737732240437195
  },
  {
    "name": "Morning Kombat",
    "icon": "https://yt3.ggpht.com/qGb1QlPmdErjmL0Nd6cbMsC12FPpTijtrHuY43y9DWKdhsTUll8XkmJNyX30LkWGuRjFUp7V=s800-c-k-c0x00ffffff-no-rj",
    "views_28": 578841,
    "views_prev_28": 599833,
    "subs_28": 295,
    "subs_prev_28": 609,
    "uploads_28": 36,
    "uploads_prev_28": 32,
    "revenue_28": 2882.6870000000004,
    "cpm_28": 6.368692307692308,
    "revenue_prev_28": 2728.6400000000003,
    "cpm_prev_28": 5.857678571428572,
    "revenue_365": 26443.786000000033,
    "cpm_365": 4.431911845730025,
    "revenue_2022": 0,
    "cpm_2022": 0.0,
    "revenue_2023": 0,
    "cpm_2023": 0.0,
    "revenue_2024": 1386.8600000000001,
    "cpm_2024": 0.22930054644808745
  },
  {
    "name": "All The Smoke Fight",
    "icon": "https://yt3.ggpht.com/tyRwrGfrQkd57eiXOUMjiHmlh6zTLJmgZ9yb5oCbUDbWdjxS3qloyti2fW8WIe-TmfgRbDo3hw=s800-c-k-c0x00ffffff-no-rj",
    "views_28": 2295670,
    "views_prev_28": 4118870,
    "subs_28": 967,
    "subs_prev_28": 3733,
    "uploads_28": 26,
    "uploads_prev_28": 46,
    "revenue_28": 7151.566000000001,
    "cpm_28": 6.189423076923078,
    "revenue_prev_28": 9463.321000000004,
    "cpm_prev_28": 5.611642857142857,
    "revenue_365": 127293.16600000003,
    "cpm_365": 6.6412865013774125,
    "revenue_2022": 0,
    "cpm_2022": 0.0,
    "revenue_2023": 0,
    "cpm_2023": 0.0,
    "revenue_2024": 74177.54999999996,
    "cpm_2024": 3.8079398907103834
  },
  {
    "name": "Ring Champs",
    "icon": "https://yt3.ggpht.com/BbGdlZ2wNgCpzri02772HfpWsK-eGUOQ-16lm4dN_H6ACEmKW8akOm_F2IcSX2TNcW-QpznNqg=s800-c-k-c0x00ffffff-no-rj",
    "views_28": 3019645,
    "views_prev_28": 8320074,
    "subs_28": 4697,
    "subs_prev_28": 11514,
    "uploads_28": 38,
    "uploads_prev_28": 46,
    "revenue_28": 3690.0249999999996,
    "cpm_28": 6.395807692307691,
    "revenue_prev_28": 4543.425,
    "cpm_prev_28": 5.756714285714286,
    "revenue_365": 13350.683000000003,
    "cpm_365": 1.8415840220385669,
    "revenue_2022": 0,
    "cpm_2022": 0.0,
    "revenue_2023": 0,
    "cpm_2023": 0.0,
    "revenue_2024": 0,
    "cpm_2024": 0.0
  },
  {
    "name": "Victor Oladipo",
    "icon": "https://yt3.ggpht.com/f-EEPiNJ33jMljawz5ikYenlzou4f-NLp2-UH-yL89WtYCwqGpU3nb32Ftx465ifap1vYMrg=s800-c-k-c0x00ffffff-no-rj",
    "views_28": 10870,
    "views_prev_28": 10289,
    "subs_28": 21,
    "subs_prev_28": -10,
    "uploads_28": 0,
    "uploads_prev_28": 0,
    "revenue_28": 0,
    "cpm_28": 0.0,
    "revenue_prev_28": 0,
    "cpm_prev_28": 0,
    "revenue_365": 1076.4579999999996,
    "cpm_365": 1.17532782369146,
    "revenue_2022": 48.87700000000006,
    "cpm_2022": 4.890561643835619,
    "revenue_2023": 18.414000000000012,
    "cpm_2023": 3.963180821917809,
    "revenue_2024": 0,
    "cpm_2024": 0.0
  },
  {
    "name": "San Antonio Spurs",
    "icon": "https://yt3.ggpht.com/dc6Tx4eGfjTkg8tpgEfNbfHwGU0FZFIKrBAmJ__0OFp15mr55gEIszxlM9IYcrfWg1zTDR69WRE=s800-c-k-c0x00ffffff-no-rj",
    "views_28": 713996,
    "views_prev_28": 713996,
    "subs_28": 788,
    "subs_prev_28": 788,
    "uploads_28": 0,
    "uploads_prev_28": 0,
    "revenue_28": 0,
    "cpm_28": 0,
    "revenue_prev_28": 0,
    "cpm_prev_28": 0,
    "revenue_365": 0,
    "cpm_365": 0,
    "revenue_2022": 0,
    "cpm_2022": 0,
    "revenue_2023": 0,
    "cpm_2023": 0,
    "revenue_2024": 0,
    "cpm_2024": 0
  }
]