[
  {
    "name": "All The Smoke",
    "icon": "https://yt3.ggpht.com/sIvQUY1CAaNlG9E5Y4wyOMp5hgtWIrp78PsGuifJL_lP1MWwYNq2FDTbbjlH66uIZm8_fFCr=s800-c-k-c0x00ffffff-no-rj",
    "views_28": 15025340,
    "views_prev_28": 11470288,
    "subs_28": 12328,
    "subs_prev_28": 9381,
    "uploads_28": 25,
    "uploads_prev_28": 72,
    "revenue_28": 43593.384000000005,
    "cpm_28": 24.44673076923077,
    "revenue_prev_28": 40296.586,
    "cpm_prev_28": 20.90839285714286,
    "revenue_365": 445368.44200000004,
    "cpm_365": 13.364303030303024,
    "revenue_2022": 0,
    "cpm_2022": 0.0,
    "revenue_2023": 0,
    "cpm_2023": 0.0,
    "revenue_2024": 230807.17100000003,
    "cpm_2024": 8.262669398907105
  },
  {
    "name": "KG Certified",
    "icon": "https://yt3.ggpht.com/yvxSfblgWpSADo_EzMMFh7vYylz_Gjp-sXqP56cvVLO8Zz6HYGL1kv3xt6ynBPwlEzbae9vv=s800-c-k-c0x00ffffff-no-rj",
    "views_28": 2009094,
    "views_prev_28": 2388085,
    "subs_28": 4306,
    "subs_prev_28": 4287,
    "uploads_28": 48,
    "uploads_prev_28": 46,
    "revenue_28": 5777.154000000001,
    "cpm_28": 10.663653846153847,
    "revenue_prev_28": 5502.564,
    "cpm_prev_28": 7.945428571428572,
    "revenue_365": 61109.789999999964,
    "cpm_365": 7.762644628099182,
    "revenue_2022": 0,
    "cpm_2022": 0.0,
    "revenue_2023": 15283.382000000001,
    "cpm_2023": 6.318002739726029,
    "revenue_2024": 19073.627999999997,
    "cpm_2024": 7.3737732240437195
  },
  {
    "name": "Morning Kombat",
    "icon": "https://yt3.ggpht.com/qGb1QlPmdErjmL0Nd6cbMsC12FPpTijtrHuY43y9DWKdhsTUll8XkmJNyX30LkWGuRjFUp7V=s800-c-k-c0x00ffffff-no-rj",
    "views_28": 931089,
    "views_prev_28": 544766,
    "subs_28": 562,
    "subs_prev_28": -25,
    "uploads_28": 41,
    "uploads_prev_28": 24,
    "revenue_28": 1730.5929999999998,
    "cpm_28": 5.631269230769231,
    "revenue_prev_28": 552.7220000000001,
    "cpm_prev_28": 5.489464285714285,
    "revenue_365": 34830.19100000002,
    "cpm_365": 6.292487603305791,
    "revenue_2022": 0,
    "cpm_2022": 0.0,
    "revenue_2023": 0,
    "cpm_2023": 0.0,
    "revenue_2024": 1386.8600000000001,
    "cpm_2024": 0.22930054644808745
  },
  {
    "name": "All The Smoke Fight",
    "icon": "https://yt3.ggpht.com/tyRwrGfrQkd57eiXOUMjiHmlh6zTLJmgZ9yb5oCbUDbWdjxS3qloyti2fW8WIe-TmfgRbDo3hw=s800-c-k-c0x00ffffff-no-rj",
    "views_28": 3742651,
    "views_prev_28": 8015821,
    "subs_28": 3498,
    "subs_prev_28": 9083,
    "uploads_28": 49,
    "uploads_prev_28": 53,
    "revenue_28": 9487.453,
    "cpm_28": 6.114884615384614,
    "revenue_prev_28": 13587.178999999998,
    "cpm_prev_28": 6.367357142857142,
    "revenue_365": 139048.1299999999,
    "cpm_365": 6.380407713498619,
    "revenue_2022": 0,
    "cpm_2022": 0.0,
    "revenue_2023": 0,
    "cpm_2023": 0.0,
    "revenue_2024": 74177.54999999996,
    "cpm_2024": 3.8079398907103834
  },
  {
    "name": "Ring Champs",
    "icon": "https://yt3.ggpht.com/WT7Zj-2bI0okGh-hz86bJfo9R4hPSKSlGTVDlo-LTeg4I9zxiNa45WkRp6HQ26AcLSv3zhvn=s800-c-k-c0x00ffffff-no-rj",
    "views_28": 2341045,
    "views_prev_28": 443584,
    "subs_28": 3031,
    "subs_prev_28": 531,
    "uploads_28": 53,
    "uploads_prev_28": 16,
    "revenue_28": 2634.65,
    "cpm_28": 5.723269230769231,
    "revenue_prev_28": 517.095,
    "cpm_prev_28": 5.139857142857144,
    "revenue_365": 21598.553999999996,
    "cpm_365": 4.568404958677684,
    "revenue_2022": 0,
    "cpm_2022": 0.0,
    "revenue_2023": 0,
    "cpm_2023": 0.0,
    "revenue_2024": 0,
    "cpm_2024": 0.0
  },
  {
    "name": "San Antonio Spurs",
    "icon": "https://yt3.ggpht.com/dc6Tx4eGfjTkg8tpgEfNbfHwGU0FZFIKrBAmJ__0OFp15mr55gEIszxlM9IYcrfWg1zTDR69WRE=s800-c-k-c0x00ffffff-no-rj",
    "views_28": 9875067,
    "views_prev_28": 7982293,
    "subs_28": 3193,
    "subs_prev_28": 4069,
    "uploads_28": 229,
    "uploads_prev_28": 278,
    "revenue_28": 0,
    "cpm_28": 0,
    "revenue_prev_28": 0,
    "cpm_prev_28": 0,
    "revenue_365": 0,
    "cpm_365": 0,
    "revenue_2022": 0,
    "cpm_2022": 0,
    "revenue_2023": 0,
    "cpm_2023": 0,
    "revenue_2024": 0,
    "cpm_2024": 0
  }
]